cellgrid/__init__.py
cellgrid/const.py
cellgrid/core.py
cellgrid/model_selection.py
cellgrid/preprocessing.py
cellgrid/ensemble/__init__.py
cellgrid/ensemble/classifier.py
cellgrid/ensemble/model.py
cellgrid/ensemble/schema.json
tests/__init__.py
tests/conftest.py
tests/test_core.py
tests/test_model_selection.py
tests/test_preprocessing.py
tests/ensemble/__init__.py
tests/ensemble/cellgrid_test.csv
tests/ensemble/cellgrid_train.csv
tests/ensemble/test_classifier.py
cellgrid-0.6.1.dist-info/AUTHORS.rst
cellgrid-0.6.1.dist-info/LICENSE
cellgrid-0.6.1.dist-info/METADATA
cellgrid-0.6.1.dist-info/WHEEL
cellgrid-0.6.1.dist-info/top_level.txt
cellgrid-0.6.1.dist-info/RECORD
