Metadata-Version: 2.1
Name: cellgrid
Version: 0.6.1
Summary: Cell classification by learning known phenotypes
Home-page: https://github.com/Brodinlab/cellgrid
Author: YC
Author-email: yang.chen@scilifelab.se
License: MIT license
Keywords: cellgrid
Platform: UNKNOWN
Classifier: Development Status :: 2 - Pre-Alpha
Classifier: Intended Audience :: Developers
Classifier: License :: OSI Approved :: MIT License
Classifier: Natural Language :: English
Classifier: Programming Language :: Python :: 3
Classifier: Programming Language :: Python :: 3.7
Classifier: Programming Language :: Python :: 3.8
Classifier: Programming Language :: Python :: 3.9
License-File: LICENSE
License-File: AUTHORS.rst
Requires-Dist: fcsy (==0.4.0)
Requires-Dist: numpy (==1.21.2)
Requires-Dist: pandas (==1.3.2)
Requires-Dist: scikit-learn (==0.24.2)
Requires-Dist: xgboost (>=0.90)
